odoo_mcp/__init__.py
odoo_mcp/__main__.py
odoo_mcp/server.py
odoo_mcp/auth/__init__.py
odoo_mcp/auth/oauth_config.py
odoo_mcp/auth/oauth_handler.py
odoo_mcp/client/__init__.py
odoo_mcp/client/odoo_client.py
odoo_mcp/config/__init__.py
odoo_mcp/config/config.py
odoo_mcp/models/__init__.py
odoo_mcp/models/domain.py
odoo_mcp/models/employee.py
odoo_mcp/models/holiday.py
odoo_mcp/models/model_info.py
odoo_mcp/resources/__init__.py
odoo_mcp/resources/models.py
odoo_mcp/resources/records.py
odoo_mcp/resources/subscriptions.py
odoo_mcp/tools/__init__.py
odoo_mcp/tools/accounting.py
odoo_mcp/tools/advanced_orm.py
odoo_mcp/tools/attachments.py
odoo_mcp/tools/automation.py
odoo_mcp/tools/batch.py
odoo_mcp/tools/cron.py
odoo_mcp/tools/execute.py
odoo_mcp/tools/export.py
odoo_mcp/tools/holiday.py
odoo_mcp/tools/messages.py
odoo_mcp/tools/metadata.py
odoo_mcp/tools/models.py
odoo_mcp/tools/realtime.py
odoo_mcp/tools/registration.py
odoo_mcp/tools/reports.py
odoo_mcp/tools/search.py
odoo_mcp/tools/security.py
odoo_mcp/tools/shell.py
odoo_mcp/tools/sql.py
odoo_mcp/tools/system.py
odoo_mcp/tools/workflow.py
odoo_mcp/tools/employee/__init__.py
odoo_mcp/tools/employee/aspire.py
odoo_mcp/tools/employee/base.py
odoo_mcp/utils/__init__.py
odoo_mcp/utils/cache.py
odoo_mcp/utils/context_helpers.py
odoo_mcp/utils/db_helpers.py
odoo_mcp/utils/logging.py
odoo_mcp_beta-0.1.2.dist-info/licenses/LICENSE
odoo_mcp_beta-0.1.2.dist-info/METADATA
odoo_mcp_beta-0.1.2.dist-info/WHEEL
odoo_mcp_beta-0.1.2.dist-info/entry_points.txt
odoo_mcp_beta-0.1.2.dist-info/top_level.txt
odoo_mcp_beta-0.1.2.dist-info/RECORD
