Metadata-Version: 2.4
Name: odoo-mcp-beta
Version: 0.1.2
Summary: MCP Server for Odoo Integration
Author-email: Ali Abdelaal <yui@kotegawa.org>
License: MIT
Project-URL: Homepage, https://github.com/ali205412/mcp-odoo
Project-URL: Issues, https://github.com/ali205412/mcp-odoo/issues
Keywords: odoo,mcp,server
Classifier: License :: OSI Approved :: MIT License
Classifier: Programming Language :: Python :: 3
Classifier: Programming Language :: Python :: 3.10
Classifier: Operating System :: OS Independent
Requires-Python: >=3.10
License-File: LICENSE
Requires-Dist: mcp>=1.6.0
Requires-Dist: requests>=2.31.0
Requires-Dist: pypi-xmlrpc==2020.12.3
Requires-Dist: anyio>=3.7.0
Provides-Extra: dev
Requires-Dist: black; extra == "dev"
Requires-Dist: isort; extra == "dev"
Requires-Dist: mypy; extra == "dev"
Requires-Dist: ruff; extra == "dev"
Requires-Dist: build; extra == "dev"
Requires-Dist: twine; extra == "dev"
Dynamic: license-file
